fake_news_detector/__init__.py
fake_news_detector/fake.py
fake_news_detector-0.0.1.dist-info/METADATA
fake_news_detector-0.0.1.dist-info/WHEEL
fake_news_detector-0.0.1.dist-info/top_level.txt
fake_news_detector-0.0.1.dist-info/RECORD
