Metadata-Version: 2.1
Name: fake-news-detector
Version: 0.0.1
Summary: This is a fake news detector trained on different languages and mainly on COVID19 domain
Home-page: https://github.com/soumayan/fake-news-detection
Author: Soumayan Bandhu Majumder
Author-email: soumayanmajumder@gmail.com
License: MIT
Platform: UNKNOWN
Classifier: Programming Language :: Python :: 3
Classifier: License :: OSI Approved :: MIT License
Classifier: Operating System :: OS Independent
Requires-Python: >=3.6
Requires-Dist: spacy (==2.3.5)
Requires-Dist: polyglot
Requires-Dist: pyicu
Requires-Dist: Morfessor
Requires-Dist: pycld2
Requires-Dist: spacytextblob (==0.1.7)
Requires-Dist: scikit-learn (==0.23.1)
